tests/.DS_Store
tests/PREN_PY/__init__.py
pren_py-0.0.1.dist-info/METADATA
pren_py-0.0.1.dist-info/WHEEL
pren_py-0.0.1.dist-info/licenses/LICENSE
pren_py-0.0.1.dist-info/RECORD
