Metadata-Version: 2.1
Name: PREN_PY
Version: 0.0.1
Summary: A small package used for a students project at HSLU Luzern
Project-URL: Homepage, https://github.com/flawas/PREN_PY
Project-URL: Issues, https://github.com/flawas/PREN_PY/issues
Author-email: Flavio Waser <waserflavio@gmail.com>
License-File: LICENSE
Classifier: License :: OSI Approved :: MIT License
Classifier: Operating System :: OS Independent
Classifier: Programming Language :: Python :: 3
Requires-Python: >=3.8
